Metadata-Version: 2.1
Name: pyonlyoffice
Version: 0.0.3
Summary: Package for working with OnlyOffice API.
Home-page: https://github.com/3v01ut10n/pyonlyoffice/
Author: 3v01ut10n
Author-email: arxonix7@gmail.com
Classifier: Programming Language :: Python :: 3.10
Classifier: License :: OSI Approved :: GNU General Public License v3 (GPLv3)
License-File: LICENSE
